nosehtml/__init__.py
nosehtml/plugin.py
NoseHTML-0.4.6.dist-info/METADATA
NoseHTML-0.4.6.dist-info/WHEEL
NoseHTML-0.4.6.dist-info/entry_points.txt
NoseHTML-0.4.6.dist-info/top_level.txt
NoseHTML-0.4.6.dist-info/RECORD
