Metadata-Version: 2.1
Name: NoseHTML
Version: 0.4.6
Summary: HTML Output plugin for Nose / Nosetests
Home-page: https://github.com/galaxyproject/nosehtml
Author: James Taylor, Nate Coraor, Dave Bouvier
Author-email: james@taylorlab.org
License: MIT
Platform: UNKNOWN
Classifier: Development Status :: 5 - Production/Stable
Classifier: Intended Audience :: Developers
Classifier: License :: OSI Approved :: MIT License
Classifier: Operating System :: OS Independent
Classifier: Programming Language :: Python :: 2
Classifier: Programming Language :: Python :: 2.7
Classifier: Programming Language :: Python :: 3
Classifier: Programming Language :: Python :: 3.5
Classifier: Programming Language :: Python :: 3.6
Classifier: Programming Language :: Python :: 3.7
Classifier: Programming Language :: Python :: 3.8
Classifier: Topic :: Software Development :: Testing
Requires-Dist: nose
